Metadata-Version: 1.0
Name: kicstextclassification
Version: 0.1
Summary: text classification in urdu
Home-page: https://github.com/minixain/UrduTextClassification
Author: minixain
Author-email: ali.ibrahim@kics.edu.pk
License: KICS
Platform: UNKNOWN
